filmfarm/__init__.py
filmfarm/link.py
filmfarm/main.py
filmfarm/models.py
filmfarm/scrape/__init__.py
filmfarm/scrape/omdb.py
filmfarm-1.0.1.dist-info/LICENSE
filmfarm-1.0.1.dist-info/METADATA
filmfarm-1.0.1.dist-info/WHEEL
filmfarm-1.0.1.dist-info/entry_points.txt
filmfarm-1.0.1.dist-info/RECORD
