Metadata-Version: 2.1
Name: filmfarm
Version: 1.0.1
Summary: A toolkit to manage movie collections.
Author: Yaniv Aknin
Author-email: yaniv@aknin.name
Requires-Python: >=3.10,<4.0
Classifier: Programming Language :: Python :: 3
Classifier: Programming Language :: Python :: 3.10
Classifier: Programming Language :: Python :: 3.11
Classifier: Programming Language :: Python :: 3.12
Requires-Dist: python-dotenv (>=1.0.1,<2.0.0)
Requires-Dist: requests (>=2.31.0,<3.0.0)
Requires-Dist: tmdbsimple (>=2.9.1,<3.0.0)
Requires-Dist: typer[shellingham] (>=0.9.0,<0.10.0)
